pyoq/__init__.py
pyoq/query.py
pyoq/test_query.py
pyoq-0.0.1.dist-info/LICENSE
pyoq-0.0.1.dist-info/METADATA
pyoq-0.0.1.dist-info/WHEEL
pyoq-0.0.1.dist-info/top_level.txt
pyoq-0.0.1.dist-info/zip-safe
pyoq-0.0.1.dist-info/RECORD
